edg/BoardCompiler.py
edg/BoardTop.py
edg/__init__.py
edg/py.typed
edg/abstract_parts/AbstractAnalogSwitch.py
edg/abstract_parts/AbstractAntenna.py
edg/abstract_parts/AbstractBjt.py
edg/abstract_parts/AbstractCapacitor.py
edg/abstract_parts/AbstractConnector.py
edg/abstract_parts/AbstractCrystal.py
edg/abstract_parts/AbstractDebugHeaders.py
edg/abstract_parts/AbstractDevices.py
edg/abstract_parts/AbstractDiodes.py
edg/abstract_parts/AbstractFerriteBead.py
edg/abstract_parts/AbstractFets.py
edg/abstract_parts/AbstractFuse.py
edg/abstract_parts/AbstractInductor.py
edg/abstract_parts/AbstractJumper.py
edg/abstract_parts/AbstractLed.py
edg/abstract_parts/AbstractLedDriver.py
edg/abstract_parts/AbstractOpamp.py
edg/abstract_parts/AbstractOscillator.py
edg/abstract_parts/AbstractPowerConverters.py
edg/abstract_parts/AbstractResistor.py
edg/abstract_parts/AbstractResistorArray.py
edg/abstract_parts/AbstractSolidStateRelay.py
edg/abstract_parts/AbstractSpiMemory.py
edg/abstract_parts/AbstractSwitch.py
edg/abstract_parts/AbstractTestPoint.py
edg/abstract_parts/AbstractTvsDiode.py
edg/abstract_parts/CanTransceiver.py
edg/abstract_parts/Categories.py
edg/abstract_parts/DigitalAmplifiers.py
edg/abstract_parts/DigitalIsolator.py
edg/abstract_parts/DummyDevices.py
edg/abstract_parts/ESeriesUtil.py
edg/abstract_parts/GateDrivers.py
edg/abstract_parts/I2cPullup.py
edg/abstract_parts/IdealIoController.py
edg/abstract_parts/IoController.py
edg/abstract_parts/IoControllerExportable.py
edg/abstract_parts/IoControllerInterfaceMixins.py
edg/abstract_parts/IoControllerMixins.py
edg/abstract_parts/IoControllerProgramming.py
edg/abstract_parts/MergedBlocks.py
edg/abstract_parts/OpampCircuits.py
edg/abstract_parts/OpampCurrentSensor.py
edg/abstract_parts/PartsTable.py
edg/abstract_parts/PartsTablePart.py
edg/abstract_parts/PassiveConnector.py
edg/abstract_parts/PassiveFilters.py
edg/abstract_parts/PinMappable.py
edg/abstract_parts/PowerCircuits.py
edg/abstract_parts/Resettable.py
edg-0.2.0.dist-info/LICENSE
edg-0.2.0.dist-info/METADATA
edg-0.2.0.dist-info/WHEEL
edg-0.2.0.dist-info/top_level.txt
edg-0.2.0.dist-info/RECORD
