Metadata-Version: 2.1
Name: edg
Version: 0.2.0
Summary: Hardware description language for circuit boards
Author-email: Ducky <richard.lin@berkeley.edu>
License: BSD 3-Clause License
Project-URL: Homepage, https://github.com/BerkeleyHCI/PolymorphicBlocks
Keywords: PCB,hardware description language
Classifier: Development Status :: 3 - Alpha
Classifier: License :: OSI Approved :: BSD License
Classifier: Topic :: Scientific/Engineering :: Electronic Design Automation (EDA)
Classifier: Typing :: Typed
Requires-Python: >=3.9
License-File: LICENSE
Requires-Dist: protobuf >=3.20.0
Requires-Dist: sexpdata ==0.0.3
Requires-Dist: Deprecated
Requires-Dist: typing-extensions
